mx_remote_manager/BayHide.py
mx_remote_manager/BayName.py
mx_remote_manager/Button.py
mx_remote_manager/ControlBar.py
mx_remote_manager/DeviceButtons.py
mx_remote_manager/DeviceDetails.py
mx_remote_manager/DeviceDetailsValue.py
mx_remote_manager/DeviceStatus.py
mx_remote_manager/Devices.py
mx_remote_manager/EdidProfile.py
mx_remote_manager/Interface.py
mx_remote_manager/Log.py
mx_remote_manager/NetworkInterface.py
mx_remote_manager/NetworkStatus.py
mx_remote_manager/Player.py
mx_remote_manager/PowerStatus.py
mx_remote_manager/Source.py
mx_remote_manager/SourceSelect.py
mx_remote_manager/Sources.py
mx_remote_manager/V2IPStats.py
mx_remote_manager/__init__.py
mx_remote_manager/const.py
mx_remote_manager/main.py
mx_remote_manager/mixins.py
mx_remote_manager/ui.gresource
mx_remote_manager/resources/svd.csv
mx_remote_manager/resources/icons/eu.opdenkamp.mx_remote_manager.ico
mx_remote_manager-1.0.0.dist-info/LICENSE
mx_remote_manager-1.0.0.dist-info/METADATA
mx_remote_manager-1.0.0.dist-info/WHEEL
mx_remote_manager-1.0.0.dist-info/entry_points.txt
mx_remote_manager-1.0.0.dist-info/top_level.txt
mx_remote_manager-1.0.0.dist-info/RECORD
