Metadata-Version: 2.1
Name: mx_remote_manager
Version: 1.0.0
Summary: Application for managing MX Remote compatible devices.
Author-email: Lars Op den Kamp <lars@opdenkamp.eu>
Maintainer-email: Lars Op den Kamp <lars@opdenkamp.eu>
License: Copyright 2024 Lars Op den Kamp <lars@opdenkamp.eu>
Project-URL: Homepage, https://github.com/opdenkamp/mx_remote_manager/
Project-URL: Documentation, https://github.com/opdenkamp/mx_remote_manager/
Project-URL: Repository, https://github.com/opdenkamp/mx_remote_manager.git
Project-URL: Bug Tracker, https://github.com/opdenkamp/mx_remote_manager/issues
Keywords: matrixos,oneip,ampos,pulse-eight
Classifier: Development Status :: 3 - Alpha
Classifier: Programming Language :: Python
Classifier: Topic :: System :: Networking :: Monitoring
Requires-Python: >=3.11
License-File: LICENSE
Requires-Dist: argparse>=1.4.0
Requires-Dist: netifaces>=0.11.0
Requires-Dist: PyGObject>=3.50.0
Requires-Dist: aes3tool>=1.1.0
Requires-Dist: pyperclip>=1.9.0
Requires-Dist: mx_remote>=2.0.0
